imagejmf/__init__.py
imagejmf/processing/__init__.py
imagejmf/processing/combination.py
imagejmf/processing/transformation.py
imagejmf/utils/__init__.py
imagejmf/utils/io.py
imagejmf/utils/plot.py
imagejmf-0.0.2.dist-info/METADATA
imagejmf-0.0.2.dist-info/WHEEL
imagejmf-0.0.2.dist-info/top_level.txt
imagejmf-0.0.2.dist-info/RECORD
